[
  {
    "word": "insurance",
    "frequency": 5,
    "group": "Cost Concerns",
    "sentiment": "entirely negative"
  },
  {
    "word": "covered",
    "frequency": 3,
    "group": "Treatment Access",
    "sentiment": "somewhat negative"
  },
  {
    "word": "copay",
    "frequency": 2,
    "group": "Financial Burden",
    "sentiment": "entirely negative"
  },
  {
    "word": "no response",
    "frequency": 2,
    "group": "Care Team",
    "sentiment": "entirely negative"
  },
  {
    "word": "desperate",
    "frequency": 2,
    "group": "Clinical Trials",
    "sentiment": "somewhat positive"
  },
  {
    "word": "access",
    "frequency": 2,
    "group": "Treatment Access",
    "sentiment": "somewhat negative"
  },
  {
    "word": "expense",
    "frequency": 2,
    "group": "Patient Empowerment",
    "sentiment": "somewhat negative"
  },
  {
    "word": "specialist",
    "frequency": 3,
    "group": "Care Experience",
    "sentiment": "neutral"
  },
  {
    "word": "prior authorization",
    "frequency": 2,
    "group": "Insurance Navigation",
    "sentiment": "entirely negative"
  },
  {
    "word": "denied",
    "frequency": 2,
    "group": "Insurance Navigation",
    "sentiment": "entirely negative"
  },
  {
    "word": "travel",
    "frequency": 3,
    "group": "Trial Logistics",
    "sentiment": "somewhat negative"
  },
  {
    "word": "research hospital",
    "frequency": 2,
    "group": "Medical Progress",
    "sentiment": "entirely positive"
  },
  {
    "word": "self-pay",
    "frequency": 1,
    "group": "Cost Workaround",
    "sentiment": "neutral"
  },
  {
    "word": "network",
    "frequency": 2,
    "group": "Provider Access",
    "sentiment": "somewhat negative"
  },
  {
    "word": "dismissive",
    "frequency": 4,
    "group": "Hope for New Treatments",
    "sentiment": "entirely negative"
  },
  {
    "word": "rushed",
    "frequency": 2,
    "group": "Care Experience",
    "sentiment": "entirely negative"
  }
]